prometheus_async/__init__.py
prometheus_async/py.typed
prometheus_async/types.py
prometheus_async/aio/__init__.py
prometheus_async/aio/_decorators.py
prometheus_async/aio/sd.py
prometheus_async/aio/web.py
prometheus_async/tx/__init__.py
prometheus_async/tx/_decorators.py
prometheus_async-22.2.0.dist-info/LICENSE
prometheus_async-22.2.0.dist-info/WHEEL
prometheus_async-22.2.0.dist-info/METADATA
prometheus_async-22.2.0.dist-info/RECORD
