Metadata-Version: 2.1
Name: prometheus-async
Version: 22.2.0
Summary: Async helpers for prometheus_client.
Keywords: metrics,prometheus,twisted,asyncio,async
Author-email: Hynek Schlawack <hs@ox.cx>
Requires-Python: >=3.7
Classifier: Development Status :: 5 - Production/Stable
Classifier: Intended Audience :: Developers
Classifier: License :: OSI Approved :: Apache Software License
Classifier: Natural Language :: English
Classifier: Operating System :: OS Independent
Classifier: Programming Language :: Python :: 3
Classifier: Programming Language :: Python :: 3.7
Classifier: Programming Language :: Python :: 3.8
Classifier: Programming Language :: Python :: 3.9
Classifier: Programming Language :: Python :: 3.10
Classifier: Programming Language :: Python :: Implementation :: CPython
Classifier: Programming Language :: Python :: Implementation :: PyPy
Classifier: Programming Language :: Python
Classifier: Topic :: Software Development :: Libraries :: Python Modules
Requires-Dist: prometheus_client >= 0.8.0
Requires-Dist: typing_extensions >= 3.10.0; python_version<'3.10'
Requires-Dist: wrapt
Requires-Dist: aiohttp>=3 ; extra == "aiohttp"
Requires-Dist: aiohttp>=3 ; extra == "consul"
Requires-Dist: pre-commit ; extra == "dev"
Requires-Dist: pytest-twisted ; extra == "dev"
Requires-Dist: tomli ; extra == "dev"
Requires-Dist: cogapp ; extra == "dev"
Requires-Dist: mypy ; extra == "dev"
Requires-Dist: coverage[toml] ; extra == "dev"
Requires-Dist: pytest ; extra == "dev"
Requires-Dist: pytest-asyncio ; extra == "dev"
Requires-Dist: aiohttp ; extra == "dev"
Requires-Dist: furo ; extra == "dev"
Requires-Dist: myst-parser ; extra == "dev"
Requires-Dist: sphinx-notfound-page ; extra == "dev"
Requires-Dist: sphinx ; extra == "dev"
Requires-Dist: sphinxcontrib-asyncio ; extra == "dev"
Requires-Dist: twisted ; extra == "dev"
Requires-Dist: aiohttp ; extra == "docs"
Requires-Dist: furo ; extra == "docs"
Requires-Dist: myst-parser ; extra == "docs"
Requires-Dist: sphinx-notfound-page ; extra == "docs"
Requires-Dist: sphinx ; extra == "docs"
Requires-Dist: sphinxcontrib-asyncio ; extra == "docs"
Requires-Dist: twisted ; extra == "docs"
Requires-Dist: coverage[toml] ; extra == "tests"
Requires-Dist: pytest ; extra == "tests"
Requires-Dist: pytest-asyncio ; extra == "tests"
Requires-Dist: twisted ; extra == "twisted"
Project-URL: Changelog, https://prometheus-async.readthedocs.io/en/stable/changelog.html
Project-URL: Documentation, https://prometheus-async.readthedocs.io/
Project-URL: Funding, https://hynek.me/say-thanks/
Project-URL: Ko-fi, https://ko-fi.com/the_hynek
Project-URL: Source Code, https://github.com/hynek/prometheus-async/
Provides-Extra: aiohttp
Provides-Extra: consul
Provides-Extra: dev
Provides-Extra: docs
Provides-Extra: tests
Provides-Extra: twisted
